canvasz/__init__.py
canvasz/core.py
canvasz-0.1.3.dist-info/METADATA
canvasz-0.1.3.dist-info/WHEEL
canvasz-0.1.3.dist-info/top_level.txt
canvasz-0.1.3.dist-info/RECORD
